{
    "education":[
        {
            "title": "Jan 2024 - Present",
            "cardTitle": "Ph.D., Computer Science",
            "cardSubtitle":"Brcok University, St. Catharines, ON, Canada",
            "cardDetailedText": "CGPA - A+",
            "icon" : {
                "src": "images/education/brock.png"
            }
        },
        {
            "title": "Sep 2022 - Oct 2023",
            "cardTitle": "M.Sc., Computer Engineering",
            "cardSubtitle":"Ontario Tech University, Oshawa, ON, Canada",
            "cardDetailedText": "GPA - A+",
            "icon" : {
                "src": "images/education/otu.png"
            }
        }
    ]
}